preconstruct/__init__.py
preconstruct/_tests/__init__.py
preconstruct/_tests/conftest.py
preconstruct/_tests/test_dataset.py
preconstruct/_tests/test_model.py
preconstruct/_tests/test_sources.py
preconstruct/_tests/test_stimuliformats.py
preconstruct/basisfunctions.py
preconstruct/dataset.py
preconstruct/sources.py
preconstruct/stimuliformats.py
preconstruct-0.3.0.dist-info/WHEEL
preconstruct-0.3.0.dist-info/METADATA
preconstruct-0.3.0.dist-info/RECORD
