Metadata-Version: 2.1
Name: preconstruct
Version: 0.3.0
Summary: preprocess auditory neurosciencd data to facilitate neural encoding/decoding models
License: MIT
Author: Dan Meliza
Author-email: cdm8j@virginia.edu
Requires-Python: >=3.8,<3.12
Classifier: License :: OSI Approved :: MIT License
Classifier: Programming Language :: Python :: 3
Classifier: Programming Language :: Python :: 3.8
Classifier: Programming Language :: Python :: 3.9
Classifier: Programming Language :: Python :: 3.10
Classifier: Programming Language :: Python :: 3.11
Requires-Dist: aiohttp (>=3.8.1,<4.0.0)
Requires-Dist: appdirs (>=1.4.4,<2.0.0)
Requires-Dist: joblib (>=1.2.0,<2.0.0)
Requires-Dist: melizalab-gammatone (>=0.1.1,<0.2.0)
Requires-Dist: numpy (>=1.21.1,<2.0.0)
Requires-Dist: pandas (>=1.3.1,<2.0.0)
Requires-Dist: parse (>=1.19.0,<2.0.0)
Requires-Dist: scipy (>=1.7.2,<2.0.0)
Requires-Dist: single-source (>=0.3.0,<0.4.0)
